__init__.py
adapters/in/__init__.py
application/__init__.py
core/__init__.py
ports/in/__init__.py
surrodocs_collector-0.1.0.dist-info/licenses/LICENSE
surrodocs_collector-0.1.0.dist-info/METADATA
surrodocs_collector-0.1.0.dist-info/WHEEL
surrodocs_collector-0.1.0.dist-info/top_level.txt
surrodocs_collector-0.1.0.dist-info/RECORD
