Metadata-Version: 2.4
Name: surrodocs-collector
Version: 0.1.0
Summary: Add your description here
Requires-Python: >=3.12
License-File: LICENSE
Requires-Dist: fastapi[standard]>=0.115.12
Dynamic: license-file
